{"trial_id": "0", "hyperparameters": {"space": [{"class_name": "Int", "config": {"name": "units", "default": null, "conditions": [], "min_value": 2, "max_value": 32, "step": 2, "sampling": "linear"}}, {"class_name": "Choice", "config": {"name": "learning_rate", "default": 0.0001, "conditions": [], "values": [0.0001, 1e-05], "ordered": true}}], "values": {"units": 18, "learning_rate": 0.0001}}, "metrics": {"metrics": {"loss": {"direction": "min", "observations": [{"value": [0.0003325181605760008], "step": 103}]}, "val_loss": {"direction": "min", "observations": [{"value": [0.0004776577407028526], "step": 103}]}}}, "score": 0.0004776577407028526, "best_step": 103, "status": "COMPLETED", "message": null}