{"trial_id": "5", "hyperparameters": {"space": [{"class_name": "Int", "config": {"name": "units", "default": null, "conditions": [], "min_value": 2, "max_value": 32, "step": 2, "sampling": "linear"}}, {"class_name": "Choice", "config": {"name": "learning_rate", "default": 0.0001, "conditions": [], "values": [0.0001, 1e-05], "ordered": true}}], "values": {"units": 12, "learning_rate": 1e-05}}, "metrics": {"metrics": {"loss": {"direction": "min", "observations": [{"value": [2.837836980819702], "step": 99}]}, "val_loss": {"direction": "min", "observations": [{"value": [0.34408894181251526], "step": 99}]}}}, "score": 0.34408894181251526, "best_step": 99, "status": "COMPLETED", "message": null}